README
setup.py
airpwn_ng.egg-info/PKG-INFO
airpwn_ng.egg-info/SOURCES.txt
airpwn_ng.egg-info/dependency_links.txt
airpwn_ng.egg-info/requires.txt
airpwn_ng.egg-info/top_level.txt
airpwn_ng/lib/core.py
airpwn_ng/lib/headers.py
airpwn_ng/lib/injector.py
airpwn_ng/lib/menu.py
airpwn_ng/lib/packet_handler.py
airpwn_ng/lib/parameters.py
airpwn_ng/lib/sniffer.py
airpwn_ng/lib/styles.py
airpwn_ng/lib/target.py
airpwn_ng/lib/visuals.py